<?xml version="1.0" encoding="UTF-8"?>
<PropertyList>
	<path>panelLights.ac</path>
	<effect>
		<inherits-from>Aircraft/Su-57/Models/Effects/panels/panels</inherits-from>
		<object-name>panelLights</object-name>
	</effect>
	<model>
		<path>Aircraft/Su-57/Models/Cockpit/Panels/Right/Lights/left.xml</path>
		<offsets>
			<x-m> 0.036</x-m>
			<y-m> 0.045</y-m>
			<z-m> 0.006</z-m>
		</offsets>
	</model>
	<model>
		<path>Aircraft/Su-57/Models/Cockpit/Panels/Right/Lights/panels.xml</path>
		<offsets>
			<x-m> 0.036</x-m>
			<y-m> 0.087</y-m>
			<z-m> 0.006</z-m>
		</offsets>
	</model>
	<model>
		<path>Aircraft/Su-57/Models/Cockpit/Panels/Right/Lights/right.xml</path>
		<offsets>
			<x-m> 0.036</x-m>
			<y-m> 0.130</y-m>
			<z-m> 0.006</z-m>
		</offsets>
	</model>
	<model>
		<path>Aircraft/Su-57/Models/Cockpit/Parts/knob1.ac</path>
		<offsets>
			<x-m> 0.083</x-m>
			<y-m> 0.046</y-m>
			<z-m> 0.006</z-m>
		</offsets>
	</model>
	<model>
		<path>Aircraft/Su-57/Models/Cockpit/Parts/knob2.ac</path>
		<offsets>
			<x-m> 0.083</x-m>
			<y-m> 0.112</y-m>
			<z-m> 0.006</z-m>
		</offsets>
	</model>
	<model>
		<path>Aircraft/Su-57/Models/Cockpit/Parts/knob2.ac</path>
		<offsets>
			<x-m> 0.086</x-m>
			<y-m> 0.185</y-m>
			<z-m> 0.006</z-m>
		</offsets>
	</model>
	<model>
		<path>Aircraft/Su-57/Models/Cockpit/Parts/button2.ac</path>
		<offsets>
			<x-m> 0.082</x-m>
			<y-m> 0.080</y-m>
			<z-m> 0.004</z-m>
		</offsets>
	</model>
	<model>
		<path>Aircraft/Su-57/Models/Cockpit/Parts/base1.gltf</path>
		<offsets>
			<x-m> 0.082</x-m>
			<y-m> 0.080</y-m>
			<z-m> 0.004</z-m>
		</offsets>
	</model>
	<model>
		<path>Aircraft/Su-57/Models/Cockpit/Panels/Right/Lights/mfd.xml</path>
		<offsets>
			<x-m> 0.082</x-m>
			<y-m> 0.142</y-m>
			<z-m> 0.004</z-m>
		</offsets>
	</model>
	<model>
		<path>Aircraft/Su-57/Models/Cockpit/Parts/switch2.gltf</path>
		<offsets>
			<x-m> 0.035</x-m>
			<y-m> 0.189</y-m>
			<z-m> 0.004</z-m>
		</offsets>
	</model>
	<model>
		<path>Aircraft/Su-57/Models/Cockpit/Parts/base1.gltf</path>
		<offsets>
			<x-m> 0.035</x-m>
			<y-m> 0.189</y-m>
			<z-m> 0.004</z-m>
		</offsets>
	</model>
	<model>
		<path>Aircraft/Su-57/Models/Cockpit/Parts/screw1.ac</path>
		<offsets>
			<x-m> 0.007</x-m>
			<y-m> 0.006</y-m>
			<z-m> 0.000</z-m>
			<heading-deg>65</heading-deg>
		</offsets>
	</model>
	<model>
		<path>Aircraft/Su-57/Models/Cockpit/Parts/screw1.ac</path>
		<offsets>
			<x-m> 0.007</x-m>
			<y-m> 0.220</y-m>
			<z-m> 0.000</z-m>
			<heading-deg>-26</heading-deg>
		</offsets>
	</model>
	<model>
		<path>Aircraft/Su-57/Models/Cockpit/Parts/screw1.ac</path>
		<offsets>
			<x-m> 0.098</x-m>
			<y-m> 0.006</y-m>
			<z-m> 0.000</z-m>
			<heading-deg>50</heading-deg>
		</offsets>
	</model>
	<model>
		<path>Aircraft/Su-57/Models/Cockpit/Parts/screw1.ac</path>
		<offsets>
			<x-m> 0.098</x-m>
			<y-m> 0.220</y-m>
			<z-m> 0.000</z-m>
			<heading-deg>63</heading-deg>
		</offsets>
	</model>
</PropertyList>
